MANIFEST.in
README.rst
setup.py
django_mailviews.egg-info/PKG-INFO
django_mailviews.egg-info/SOURCES.txt
django_mailviews.egg-info/dependency_links.txt
django_mailviews.egg-info/not-zip-safe
django_mailviews.egg-info/requires.txt
django_mailviews.egg-info/top_level.txt
mailviews/__init__.py
mailviews/helpers.py
mailviews/messages.py
mailviews/models.py
mailviews/previews.py
mailviews/utils.py
mailviews/static/mailviews/css/.gitignore
mailviews/static/mailviews/css/bootstrap.css
mailviews/static/mailviews/css/mailviews.css
mailviews/static/mailviews/img/.gitignore
mailviews/static/mailviews/img/glyphicons-halflings-white.png
mailviews/static/mailviews/img/glyphicons-halflings.png
mailviews/static/mailviews/javascript/.gitignore
mailviews/static/mailviews/javascript/bootstrap-affix.js
mailviews/static/mailviews/javascript/bootstrap-alert.js
mailviews/static/mailviews/javascript/bootstrap-button.js
mailviews/static/mailviews/javascript/bootstrap-carousel.js
mailviews/static/mailviews/javascript/bootstrap-collapse.js
mailviews/static/mailviews/javascript/bootstrap-dropdown.js
mailviews/static/mailviews/javascript/bootstrap-modal.js
mailviews/static/mailviews/javascript/bootstrap-popover.js
mailviews/static/mailviews/javascript/bootstrap-scrollspy.js
mailviews/static/mailviews/javascript/bootstrap-tab.js
mailviews/static/mailviews/javascript/bootstrap-tooltip.js
mailviews/static/mailviews/javascript/bootstrap-transition.js
mailviews/static/mailviews/javascript/bootstrap-typeahead.js
mailviews/static/mailviews/javascript/jquery.js
mailviews/templates/mailviews/base.html
mailviews/templates/mailviews/previews/detail.html
mailviews/templates/mailviews/previews/list.html
mailviews/templatetags/__init__.py
mailviews/templatetags/mailviews.py
mailviews/tests/__init__.py
mailviews/tests/__main__.py
mailviews/tests/manage.py
mailviews/tests/tests.py
mailviews/tests/urls.py
mailviews/tests/utils.py
mailviews/tests/emails/__init__.py
mailviews/tests/emails/previews.py
mailviews/tests/emails/views.py