Metadata-Version: 1.0
Name: django-mailviews
Version: 0.6.5
Summary: Class-based mail views for Django
Home-page: http://github.com/disqus/django-mailviews/
Author: ted kaemming
Author-email: ted@disqus.com
License: Apache License 2.0
Platform: UNKNOWN
